launchscreen/__init__.py
launchscreen/launchscreen.py
launchscreen-1.0.8.dist-info/LICENSE
launchscreen-1.0.8.dist-info/METADATA
launchscreen-1.0.8.dist-info/WHEEL
launchscreen-1.0.8.dist-info/top_level.txt
launchscreen-1.0.8.dist-info/RECORD
