Metadata-Version: 2.1
Name: launchscreen
Version: 1.0.8
Summary: Launch Screen for Tkinter
Home-page: https://github.com/mahinbinhasan/launchscreen
Author: Mahin Bin Hasan (mahinbinhasan)
Author-email: <allmahin149@gmail.com>
License: MIT
Keywords: python,launchscreen,tkstartingwindow,transparent window
Classifier: License :: OSI Approved :: MIT License
Classifier: Programming Language :: Python :: 3
License-File: LICENSE
